genoray_cli/__init__.py
genoray_cli/__main__.py
genoray_cli-0.1.2.dist-info/METADATA
genoray_cli-0.1.2.dist-info/WHEEL
genoray_cli-0.1.2.dist-info/entry_points.txt
genoray_cli-0.1.2.dist-info/licenses/LICENSE
genoray_cli-0.1.2.dist-info/RECORD
