Metadata-Version: 2.4
Name: genoray-cli
Version: 0.1.2
Summary: Command line interface for genoray
Author-email: David Laub <dlaub@ucsd.edu>
License: MIT License
License-File: LICENSE
Requires-Python: <3.13,>=3.9
Requires-Dist: cyclopts
Requires-Dist: genoray
